{
  "headers": {
    "server": "deno/gcp-europe-north1",
    "content-length": "488",
    "age": "193889",
    "access-control-allow-origin": "*",
    "date": "Sat, 02 Dec 2023 04:04:21 GMT",
    "accept-ranges": "bytes",
    "cross-origin-opener-policy": "same-origin",
    "x-amz-replication-status": "COMPLETED",
    "cross-origin-resource-policy": "same-origin",
    "etag": "\"184b62d4fff3703096fb90beeacee50e\"",
    "strict-transport-security": "max-age=63072000; includeSubDomains; preload",
    "x-amz-cf-id": "ir0fWvJk5j4-fy6pjvc3bkshrCtFuIzboM0Gat65ol2y27yXFjb-VQ==",
    "cache-control": "public, max-age=31536000, immutable",
    "x-cache": "Hit from cloudfront",
    "content-type": "application/typescript; charset=utf-8",
    "cross-origin-embedder-policy": "same-origin",
    "last-modified": "Thu, 24 Aug 2023 15:44:13 GMT",
    "server-timing": "fetchSource;dur=16",
    "referrer-policy": "strict-origin-when-cross-origin",
    "vary": "Accept-Encoding, Origin",
    "via": "http/2 edgeproxy-h",
    "x-amz-cf-pop": "ARN1-C1",
    "x-amz-server-side-encryption": "AES256",
    "x-content-type-options": "nosniff",
    "x-amz-version-id": "mGRIYAeFjXLZTZd2bh4Y34isdL8wLcJ.",
    "content-security-policy": "default-src 'none'; style-src 'unsafe-inline'; sandbox",
    "x-frame-options": "DENY"
  },
  "url": "https://deno.land/std@0.200.0/path/to_namespaced_path.ts",
  "now": {
    "secs_since_epoch": 1701683749,
    "nanos_since_epoch": 459550334
  }
}