{
  "headers": {
    "x-content-type-options": "nosniff",
    "accept-ranges": "bytes",
    "cross-origin-opener-policy": "same-origin",
    "cache-control": "public, max-age=31536000, immutable",
    "cross-origin-embedder-policy": "same-origin",
    "etag": "\"0d77674f3656c982a16001a3b289397b\"",
    "x-frame-options": "DENY",
    "referrer-policy": "strict-origin-when-cross-origin",
    "age": "162451",
    "content-type": "application/typescript; charset=utf-8",
    "access-control-allow-origin": "*",
    "server": "deno/gcp-europe-north1",
    "server-timing": "fetchSource;dur=108",
    "content-length": "1151",
    "strict-transport-security": "max-age=63072000; includeSubDomains; preload",
    "x-amz-cf-id": "MMbylXMIDGO9nCspjs3-DD6hXYDyTZ9nF1kGr1sJbplQdQsxo5Q2zw==",
    "x-amz-cf-pop": "ARN1-C1",
    "x-amz-replication-status": "COMPLETED",
    "last-modified": "Fri, 25 Mar 2022 13:32:48 GMT",
    "x-amz-version-id": "N_aVitwjyCoPFwdfRssFIdQB8mi1BUO9",
    "x-cache": "Hit from cloudfront",
    "date": "Sat, 02 Dec 2023 12:48:18 GMT",
    "content-security-policy": "default-src 'none'; style-src 'unsafe-inline'; sandbox",
    "cross-origin-resource-policy": "same-origin",
    "via": "http/2 edgeproxy-h",
    "vary": "Accept-Encoding, Origin"
  },
  "url": "https://deno.land/std@0.132.0/node/_fs/_fs_link.ts",
  "now": {
    "secs_since_epoch": 1701683749,
    "nanos_since_epoch": 170152500
  }
}